rria_api_denso/__init__.py
rria_api_denso/action_denso.py
rria_api_denso/connect_denso.py
rria_api_denso/robot_object.py
rria_api_denso/utils/__init__.py
rria_api_denso/utils/bcapclient.py
rria_api_denso/utils/orinexception.py
rria_api_denso/utils/variant.py
rria_api_denso-0.1.1.dist-info/METADATA
rria_api_denso-0.1.1.dist-info/WHEEL
rria_api_denso-0.1.1.dist-info/RECORD
