Metadata-Version: 2.1
Name: rria-api-denso
Version: 0.1.1
Summary: 
Author: Felipe Augusto
Author-email: 97059009+felipeadsm@users.noreply.github.com
Requires-Python: >=3.11,<4.0
Classifier: Programming Language :: Python :: 3
Classifier: Programming Language :: Python :: 3.11
Requires-Dist: pywin32 (>=306,<307)
